scorio/__init__.py
scorio/eval.py
scorio/rank.py
scorio/utils.py
scorio-0.1.0.dist-info/licenses/LICENSE
scorio-0.1.0.dist-info/METADATA
scorio-0.1.0.dist-info/WHEEL
scorio-0.1.0.dist-info/top_level.txt
scorio-0.1.0.dist-info/RECORD
