Metadata-Version: 2.4
Name: scorio
Version: 0.1.0
Summary: Bayesian evaluation and ranking toolkit
Author-email: Mohsen Hariri <mohsen.hariri@case.edu>, Amirhossein Samandar <amirhossein.samandar@case.edu>
License-Expression: MIT
Project-URL: Homepage, https://scorio.readthedocs.io/
Project-URL: Repository, https://github.com/mohsenhariri/scorio
Project-URL: Issues, https://github.com/mohsenhariri/scorio/issues
Project-URL: Documentation, https://scorio.readthedocs.io/
Keywords: bayesian,statistics,ranking,evaluation,machine learning,large language models
Classifier: Programming Language :: Python :: 3.9
Classifier: Programming Language :: Python :: 3.10
Classifier: Programming Language :: Python :: 3.11
Classifier: Programming Language :: Python :: 3.12
Classifier: Programming Language :: Python :: 3.13
Classifier: Intended Audience :: Developers
Classifier: Intended Audience :: Information Technology
Classifier: Intended Audience :: Science/Research
Classifier: Topic :: Scientific/Engineering
Classifier: Topic :: Scientific/Engineering :: Artificial Intelligence
Classifier: Topic :: Scientific/Engineering :: Information Analysis
Classifier: Topic :: Scientific/Engineering :: Mathematics
Classifier: Topic :: Software Development :: Libraries :: Python Modules
Requires-Python: <3.14,>=3.9
License-File: LICENSE
Requires-Dist: numpy
Requires-Dist: scipy
Provides-Extra: dev
Requires-Dist: pytest>=7.0; extra == "dev"
Requires-Dist: black>=24.0; extra == "dev"
Requires-Dist: isort>=5.0; extra == "dev"
Requires-Dist: mypy>=1.0; extra == "dev"
Dynamic: license-file
